{
    "difficulty": "0x400",
    "alloc": {
        "Eaf6e1799A19C5D91e262703f27Ab5EB62e27E18": {
            "balance": "0xF453625CFFC4F000000"
        },
        "430A59d0E22D682cF916Ec353fd06B6f15361a15": {
            "balance": "0xF453625CFFC4F000000"
        },
        "3787304aBC26036d21B3C52F8aE1757Ee6f821e4": {
            "balance": "0xF453625CFFC4F000000"
        },
        "4BA08968a7dBdE2BB38c93578bc222043B593f14": {
            "balance": "0xF453625CFFC4F000000"
        },
        "7CC101aC9167D281D7fAc35531A5E9F19B02d830": {
            "balance": "0xF453625CFFC4F000000"
        }
    },
    "gasLimit": "0xfffffffffffff",
    "config": {
        "chainId": 4002
    }
}
